[
  { "id": "sunset-glow", "name": "ಮುಸ್ಸಂಜೆಯ ರಾಗ", "colors": ["#FF6B6B", "#FFE66D"] },
  { "id": "ocean-depths", "name": "ಸಾಗರದ ಒಡಲು", "colors": ["#2193b0", "#6dd5ed"] },
  { "id": "lush-forest", "name": "ಹಸಿರು ವನಸಿರಿ", "colors": ["#11998e", "#38ef7d"] },
  { "id": "royal-purple", "name": "ರಾಜವೈಭವ ನೇರಳೆ", "colors": ["#6441A5", "#2a0845"] },
  { "id": "midnight-city", "name": "ನಡುರಾತ್ರಿಯ ನಗರಿ", "colors": ["#232526", "#414345"] },
  { "id": "raspberry-sorbet", "name": "ರಾಸ್ಪ್‌ಬೆರಿ ತಂಪು", "colors": ["#8E2DE2", "#4A00E0"] },
  { "id": "morning-sky", "name": "ಮುಂಜಾನೆಯ ಮುಗಿಲು", "colors": ["#FF5F6D", "#FFC371"] },
  { "id": "frozen-lake", "name": "ಹಿಮದ ಸರೋವರ", "colors": ["#E0EAFC", "#CFDEF3"] },
  { "id": "burning-orange", "name": "ಉರಿಯುವ ಕಿತ್ತಳೆ", "colors": ["#FF416C", "#FF4B2B"] },
  { "id": "electric-neon", "name": "ಮಿಂಚುವ ನಿಯಾನ್", "colors": ["#00F260", "#0575E6"] },
  { "id": "deep-space", "name": "ಅನಂತ ಕತ್ತಲು", "colors": ["#000000", "#434343"] },
  { "id": "soft-candy", "name": "ಮೆತ್ತನೆಯ ಸಿಹಿ", "colors": ["#D66D75", "#E29587"] },
  { "id": "cyber-punk", "name": "ಸೈಬರ್ ರಂಗು", "colors": ["#7F00FF", "#E100FF"] },
  { "id": "desert-sand", "name": "ಮರುಭೂಮಿಯ ಮರಳು", "colors": ["#edc891", "#94716b"] },
  { "id": "cool-blues", "name": "ತಂಗಾಳಿ ನೀಲಿ", "colors": ["#2F80ED", "#56CCF2"] },
  { "id": "amethyst-dream", "name": "ನೇರಳೆ ಕನಸು", "colors": ["#9b5de5", "#8338ec"] },
  { "id": "pink-peach", "name": "ಗುಲಾಬಿ ಮುಸ್ಸಂಜೆ", "colors": ["#ffb347", "#ee2f8e"] },
  { "id": "lime-green-glow", "name": "ನಿಂಬೆ ಹಸಿರು ಹೊಳಪು", "colors": ["#ccff00", "#78b700"] },
  { "id": "emerald-teal", "name": "ಪಚ್ಚೆ ನೀಲಿ", "colors": ["#00b894", "#18bc9c"] },
  { "id": "crimson-sunrise", "name": "ಕೆಂಪೇರಿದ ಮುಂಜಾನೆ", "colors": ["#e1525a", "#e84c22"] },
  { "id": "strawberry-cream", "name": "ಸ್ಟ್ರಾಬೆರಿ ಕೆನೆ", "colors": ["#f199b0", "#ed58a2"] },
  { "id": "mint-meadow", "name": "ಪುದೀನ ವನ", "colors": ["#37d498", "#17a589"] },
  { "id": "sun-kissed-beach", "name": "ಬಿಸಿಲು ಕಡಲತೀರ", "colors": ["#f7c6ac", "#fee17a"] },
  { "id": "cotton-candy-clouds", "name": "ಹತ್ತಿ ಮಿಠಾಯಿ ಮುಗಿಲು", "colors": ["#ffc2e0", "#e05697"] },
  { "id": "magenta-fever", "name": "ಮೆಜೆಂಟಾ ಮಾಯೆ", "colors": ["#ff73ff", "#ee00dd"] },
  { "id": "aqua-haze", "name": "ನೀಲಿ ಮಂಜು", "colors": ["#34e8e8", "#2cbebe"] },
  { "id": "celestial-breeze", "name": "ಸ್ವರ್ಗೀಯ ತಂಗಾಳಿ", "colors": ["#b4d4f7", "#5cacf3"] },
  { "id": "solar-flare", "name": "ಸೌರ ಜ್ವಾಲೆ", "colors": ["#fba693", "#fe8c00"] },
  { "id": "blush-bloom", "name": "ನಾಚಿಕೆಯ ಹೂವು", "colors": ["#fba4b4", "#f36d9d"] },
  { "id": "ice-crystal", "name": "ಹಿಮದ ಹರಳು", "colors": ["#cdeafc", "#96d6fc"] },
  { "id": "electric-stream", "name": "ಮಿಂಚಿನ ಪ್ರವಾಹ", "colors": ["#0fffe9", "#0084f8"] },
  { "id": "neon-nebula", "name": "ನಿಯಾನ್ ತಾರಾಮಂಡಲ", "colors": ["#e010a3", "#bc13fe"] },
  { "id": "phoenix-blaze", "name": "ಅಗ್ನಿಪಕ್ಷಿಯ ಜ್ವಾಲೆ", "colors": ["#ff3f00", "#ffa500"] },
  { "id": "chartreuse-ripple", "name": "ಹಸಿರು ಅಲೆ", "colors": ["#79d70f", "#d3f101"] },
  { "id": "oceanic-abyss", "name": "ಮಹಾಸಾಗರದ ಒಡಲು", "colors": ["#00a2ff", "#0000ff"] },
  { "id": "golden-ember", "name": "ಚಿನ್ನದ ಕೆಂಡ", "colors": ["#ff4b1f", "#ff9068"] },
  { "id": "tangerine-dream", "name": "ಕಿತ್ತಳೆ ಕನಸು", "colors": ["#ff8c00", "#ffff00"] },
  { "id": "deep-teal", "name": "ಗಾಢ ಹಸಿರುನೀಲಿ", "colors": ["#00d2ff", "#3a7bd5"] },
  { "id": "gold-fever", "name": "ಸ್ವರ್ಣದ ಹೊಳಪು", "colors": ["#f4c724", "#ccff00"] },
  { "id": "sakura-pinnacle", "name": "ಚೆರ್ರಿ ಹೂವಿನ ಶಿಖರ", "colors": ["#ffc2d1", "#ffe5ec"] },
  { "id": "rose-parade", "name": "ಗುಲಾಬಿ ಉತ್ಸವ", "colors": ["#ff00f7", "#ffc0cb"] },
  { "id": "oceanic-flow", "name": "ಕಡಲ ಅಲೆಗಳ ಹರಿವು", "colors": ["#43cea2", "#185a9d"] },
  { "id": "indigo-midnight", "name": "ಗಾಢನೀಲಿ ನಡುರಾತ್ರಿ", "colors": ["#7209b7", "#3a0ca3"] },
  { "id": "golden-dusk", "name": "ಹೊಂಬಣ್ಣದ ಮುಸ್ಸಂಜೆ", "colors": ["#fdc830", "#f37335"] },
  { "id": "rose-quartz-flow", "name": "ಗುಲಾಬಿ ಹರಳಿನ ಹರಿವು", "colors": ["#fb65e9", "#fba693"] },
  { "id": "ice-blue-dream", "name": "ಹಿಮ ನೀಲಿಯ ಕನಸು", "colors": ["#d9eeff", "#a5d8ff"] },
  { "id": "electric-indigo", "name": "ಮಿಂಚುವ ಗಾಢನೀಲಿ", "colors": ["#00c6ff", "#0072ff"] },
  { "id": "crimson-tide", "name": "ಕೆಂಪು ಅಲೆ", "colors": ["#FF0000", "#D3343B"] },
  { "id": "blood-moon", "name": "ರಕ್ತ ಚಂದ್ರ", "colors": ["#FF0000", "#C90000"] },
  { "id": "dark-ruby", "name": "ಕಡು ಮಾಣಿಕ್ಯ", "colors": ["#FF0011", "#A0001F"] },
  { "id": "fire-brick", "name": "ಬೆಂಕಿಯ ಜ್ವಾಲೆ", "colors": ["#8A0018", "#F13729"] },
  { "id": "deep-ocean", "name": "ಆಳ ಸಾಗರ", "colors": ["#2532A6", "#615EFC"] },
  { "id": "sky-dive", "name": "ನೀಲಿ ಮುಗಿಲು", "colors": ["#4BC4F0", "#0434BB"] },
  { "id": "blue-lagoon", "name": "ನೀಲಿ ಸರೋವರ", "colors": ["#3054F0", "#A2C1FF"] },
  { "id": "cyan-breeze", "name": "ತಂಪಾದ ಗಾಳಿ", "colors": ["#61E8F2", "#40B9CF"] },
  { "id": "purple-sunset", "name": "ನೇರಳೆ ಮುಸ್ಸಂಜೆ", "colors": ["#FF0000", "#A724FF"] },
  { "id": "watermelon-sugar", "name": "ಕಲ್ಲಂಗಡಿ ಸಿಹಿ", "colors": ["#00F0B5", "#C90000"] },
  { "id": "burning-fire", "name": "ಉರಿಯುವ ಬೆಂಕಿ", "colors": ["#FF0011", "#FFC800"] },
  { "id": "neon-pink", "name": "ಮಿಂಚುವ ಗುಲಾಬಿ", "colors": ["#FF00DD", "#F12729"] },
  { "id": "earth-to-sky", "name": "ಮಣ್ಣು ಮತ್ತು ಮುಗಿಲು", "colors": ["#F49000", "#0A6DF9"] },
  { "id": "lemon-lime", "name": "ನಿಂಬೆ ಹಸಿರು", "colors": ["#4BC4F0", "#EFFF00"] },
  { "id": "retro-wave", "name": "ಹಳೆಯ ನೆನಪು", "colors": ["#3024F0", "#FC00FC"] },
  { "id": "cotton-candy-light", "name": "ಹತ್ತಿ ಮಿಠಾಯಿ", "colors": ["#F2A8D9", "#90B9F9"] },
  { "id": "sunrise-glow", "name": "ಸೂರ್ಯೋದಯದ ಕಾಂತಿ", "colors": ["#FFB6D9", "#F9FF00"] },
  { "id": "spring-meadow", "name": "ವಸಂತದ ಹುಲ್ಲುಗಾವಲು", "colors": ["#DAFF00", "#48D02B"] },
  { "id": "royal-twilight", "name": "ರಾಜ ಮುಸ್ಸಂಜೆ", "colors": ["#8E00FF", "#FF9D00"] },
  { "id": "mango-sweet", "name": "ಮಾವಿನ ಸಿಹಿ", "colors": ["#FFE000", "#FF0087"] },
  { "id": "fresh-mint", "name": "ತಾಜಾ ಪುದೀನ", "colors": ["#00CD63", "#44ED9C"] },
  { "id": "forest-canopy", "name": "ಕಾಡಿನ ಮೇಲಾವರಣ", "colors": ["#79FF90", "#00A357"] },
  { "id": "jungle-depths", "name": "ಕಾಡಿನ ಆಳ", "colors": ["#00B520", "#008F00"] },
  { "id": "olive-grove", "name": "ಹಸಿರು ತೋಟ", "colors": ["#81E52E", "#1C6800"] },
  { "id": "sun-beam", "name": "ಸೂರ್ಯನ ಕಿರಣ", "colors": ["#FFF200", "#F9FF00"] },
  { "id": "golden-hour", "name": "ಸುವರ್ಣ ಘಳಿಗೆ", "colors": ["#FFE700", "#E3FF00"] },
  { "id": "yellow-daisy", "name": "ಹಳದಿ ಹೂವು", "colors": ["#FFE980", "#FFD000"] },
  { "id": "morning-light", "name": "ಬೆಳಗಿನ ಬೆಳಕು", "colors": ["#FFE350", "#FFF880"] }
]
